smoky.cp39-win_amd64.pyd
smoky.build/.gitignore
smoky-0.1.3.dist-info/METADATA
smoky-0.1.3.dist-info/WHEEL
smoky-0.1.3.dist-info/top_level.txt
smoky-0.1.3.dist-info/RECORD
